build_backend.py
torch_c_dlpack_ext/__init__.py
torch_c_dlpack_ext/core.py
torch_c_dlpack_ext/libtorch_c_dlpack_addon_torch27-cpu.so
torch_c_dlpack_ext/libtorch_c_dlpack_addon_torch27-cuda.so
torch_c_dlpack_ext/libtorch_c_dlpack_addon_torch28-cpu.so
torch_c_dlpack_ext/libtorch_c_dlpack_addon_torch28-cuda.so
torch_c_dlpack_ext-0.1.4.dist-info/METADATA
torch_c_dlpack_ext-0.1.4.dist-info/WHEEL
torch_c_dlpack_ext-0.1.4.dist-info/top_level.txt
torch_c_dlpack_ext-0.1.4.dist-info/RECORD
