Metadata-Version: 2.4
Name: torch_c_dlpack_ext
Version: 0.1.4
Summary: torch c dlpack ext
Requires-Python: >=3.9
Requires-Dist: torch
